tf_literature_based_discovery/__init__.py
tf_literature_based_discovery/interaction_views.py
tf_literature_based_discovery/library.py
tf_literature_based_discovery/urls.py
tf_literature_based_discovery/views.py
tf_literature_based_discovery/visualization_views.py
tf_literature_based_discovery/lib/__init__.py
tf_literature_based_discovery/lib/heuristics/__init__.py
tf_literature_based_discovery/lib/heuristics/band_matrices.py
tf_literature_based_discovery/lib/heuristics/banded_matrix_heuristics.py
tf_literature_based_discovery/lib/heuristics/diagonalization_helpers.py
tf_literature_based_discovery/lib/heuristics/frequency_heuristics.py
tf_literature_based_discovery/lib/heuristics/heuristic_calculations.py
tf_literature_based_discovery/lib/heuristics/memoizator.py
tf_literature_based_discovery/lib/heuristics/misclassification_indices.py
tf_literature_based_discovery/lib/heuristics/outlier_heuristics.py
tf_literature_based_discovery/lib/heuristics/similarity_heuristics.py
tf_literature_based_discovery/lib/heuristics/test.py
tf_literature_based_discovery/lib/heuristics/tfidf_heuristics.py
tf_literature_based_discovery/package_data/categories/1685efd9-cbfb-4e52-bcee-a29a87087a55.json
tf_literature_based_discovery/package_data/categories/23a64dd1-2764-4e22-90c5-f395da1c7dae.json
tf_literature_based_discovery/package_data/categories/3f354ad3-aab3-43fe-aeb8-b5183cb185be.json
tf_literature_based_discovery/package_data/categories/d3a0f587-3911-437e-b123-622b6bbc3068.json
tf_literature_based_discovery/package_data/widgets/053f7571-b7a4-4367-a829-abe29d437a02.json
tf_literature_based_discovery/package_data/widgets/079aae7d-aaa3-4f3c-9990-7bc976bbbba1.json
tf_literature_based_discovery/package_data/widgets/29c7fd5c-99ed-4bf1-b0ac-0c16e431aff4.json
tf_literature_based_discovery/package_data/widgets/3d341f7b-7992-42a7-b3db-c3c5217e9603.json
tf_literature_based_discovery/package_data/widgets/614f692b-07b5-496a-b0d3-a64199adaf62.json
tf_literature_based_discovery-0.0.6.dist-info/DESCRIPTION.rst
tf_literature_based_discovery-0.0.6.dist-info/METADATA
tf_literature_based_discovery-0.0.6.dist-info/RECORD
tf_literature_based_discovery-0.0.6.dist-info/WHEEL
tf_literature_based_discovery-0.0.6.dist-info/metadata.json
tf_literature_based_discovery-0.0.6.dist-info/top_level.txt
